{"formImage":{"Transcoder":"pdf2json@1.1.7 [https://github.com/modesty/pdf2json]","Agency":"","Id":{"AgencyId":"","Name":"","MC":false,"Max":1,"Parent":""},"Pages":[{"Height":52.622,"HLines":[{"x":26.543,"y":48.078,"w":1.5,"l":5.316},{"x":26.543,"y":45.899,"w":1.5,"l":5.316},{"x":15.887,"y":48.078,"w":1.5,"l":5.316},{"x":15.887,"y":45.899,"w":1.5,"l":5.316},{"x":5.231,"y":48.078,"w":1.5,"l":5.316},{"x":5.231,"y":45.899,"w":1.5,"l":5.316},{"x":21.231,"y":48.078,"w":1.5,"l":5.316},{"x":21.231,"y":45.899,"w":1.5,"l":5.316},{"x":10.543,"y":48.078,"w":1.5,"l":5.316},{"x":10.543,"y":45.898,"w":1.5,"l":5.316},{"x":1.047,"y":4.633,"w":1.5,"l":34.047},{"x":5.234,"y":50.953,"w":1.5,"l":9.586},{"x":22.281,"y":50.953,"w":1.5,"l":9.586},{"x":10.406,"y":3.703,"w":1.5,"l":16.219},{"x":0.813,"y":5.622,"w":1.5,"l":35},{"x":0.813,"y":9.434,"w":1.5,"l":35},{"x":0.813,"y":6.247,"w":1.5,"l":35},{"x":0.938,"y":9.059,"w":1.5,"l":25}],"VLines":[{"x":31.859,"y":45.899,"w":1.5,"l":2.179},{"x":26.543,"y":45.899,"w":1.5,"l":2.179},{"x":21.203,"y":45.899,"w":1.5,"l":2.179},{"x":15.887,"y":45.899,"w":1.5,"l":2.179},{"x":10.547,"y":45.899,"w":1.5,"l":2.179},{"x":5.231,"y":45.899,"w":1.5,"l":2.179},{"x":26.547,"y":45.899,"w":1.5,"l":2.179},{"x":21.231,"y":45.899,"w":1.5,"l":2.179},{"x":15.859,"y":45.898,"w":1.5,"l":2.18},{"x":10.543,"y":45.898,"w":1.5,"l":2.18},{"x":6.922,"y":4.633,"w":1.5,"l":0.922},{"x":9.172,"y":4.633,"w":1.5,"l":0.922},{"x":11.266,"y":4.633,"w":1.5,"l":0.898},{"x":15.484,"y":4.633,"w":1.5,"l":0.922},{"x":0.813,"y":5.622,"w":1.5,"l":3.813},{"x":35.813,"y":5.622,"w":1.5,"l":3.813},{"x":10.813,"y":6.247,"w":1.5,"l":1.25}],"Fills":[{"x":0,"y":0,"w":0,"h":0,"clr":1},{"x":0.864,"y":0.614,"w":5.376,"h":1.882,"clr":1},{"x":28.938,"y":6.434,"w":6.3,"h":1.25,"clr":0}],"Texts":[{"x":11.516,"y":1.4220000000000002,"w":142.828,"sw":0.40625,"clr":0,"A":"left","R":[{"T":"LISTA%20DE%20ENTREGA%20N%C2%BA","S":-1,"TS":[0,17,0,0]}]},{"x":1.039,"y":1.391,"w":40.28,"sw":0.38021875,"clr":0,"A":"left","R":[{"T":"JADLOG","S":10,"TS":[0,14,1,0]}]},{"x":1.016,"y":1.6560000000000001,"w":69.11,"sw":0.40625,"clr":0,"A":"left","R":[{"T":"A%20sua%20encomenda%20na%201%C2%AA%20classe.","S":1,"TS":[0,8,0,0]}]},{"x":0.8360000000000001,"y":4.539,"w":47.655,"sw":0.40625,"clr":0,"A":"left","R":[{"T":"DESCRI%C3%87%C3%83O","S":3,"TS":[0,12,0,0]}]},{"x":6.906,"y":4.524,"w":17.712,"sw":0.40625,"clr":0,"A":"left","R":[{"T":"QTD","S":3,"TS":[0,12,0,0]}]},{"x":9.078,"y":4.524,"w":21.384,"sw":0.40625,"clr":0,"A":"left","R":[{"T":"PESO","S":3,"TS":[0,12,0,0]}]},{"x":11.196,"y":4.524,"w":41.922,"sw":0.40625,"clr":0,"A":"left","R":[{"T":"TELEFONE","S":3,"TS":[0,12,0,0]}]},{"x":15.414,"y":4.531,"w":31.401,"sw":0.40625,"clr":0,"A":"left","R":[{"T":"CIDADE","S":3,"TS":[0,12,0,0]}]},{"x":27.039,"y":4.555,"w":111.285,"sw":0.40625,"clr":0,"A":"left","R":[{"T":"AGENDADA%20%20%20%20%20%20%20%20%20%20PERIODO","S":3,"TS":[0,12,0,0]}]},{"x":6.149,"y":45.711,"w":43.038,"sw":0.40625,"clr":0,"A":"left","R":[{"T":"REMESSAS","S":3,"TS":[0,12,0,0]}]},{"x":11.664,"y":45.703,"w":39.087,"sw":0.40625,"clr":0,"A":"left","R":[{"T":"VOLUMES","S":3,"TS":[0,12,0,0]}]},{"x":16.758,"y":45.696,"w":50.913,"sw":0.40625,"clr":0,"A":"left","R":[{"T":"PESO%20TOTAL","S":3,"TS":[0,12,0,0]}]},{"x":21.656,"y":45.727,"w":63.945,"sw":0.40625,"clr":0,"A":"left","R":[{"T":"FRETE%20A%20PAGAR","S":3,"TS":[0,12,0,0]}]},{"x":27.234,"y":45.711,"w":53.55,"sw":0.40625,"clr":0,"A":"left","R":[{"T":"DEVOLVIDOS","S":3,"TS":[0,12,0,0]}]},{"x":7.359,"y":50.766,"w":62.63,"sw":0.40625,"clr":0,"A":"left","R":[{"T":"ENTREGADOR","S":-1,"TS":[0,13,0,0]}]},{"x":25.094,"y":50.758,"w":60.48,"sw":0.40625,"clr":0,"A":"left","R":[{"T":"CONFERENTE","S":-1,"TS":[0,13,0,0]}]},{"x":28.863,"y":47.563,"w":44.328,"sw":0.40625,"clr":0,"A":"left","R":[{"T":"Tecnologia%20JADLOG%20-%20by%20RicardoF","S":0,"TS":[0,6,0,0]}]},{"x":0.688,"y":5.309,"w":36.176,"sw":0.32553125,"clr":0,"A":"left","R":[{"T":"DIVERSOS","S":2,"TS":[0,10,0,0]}]},{"x":7.438,"y":5.309,"w":3.892,"sw":0.32553125,"clr":0,"A":"left","R":[{"T":"1","S":2,"TS":[0,10,0,0]}]},{"x":9.625,"y":5.309,"w":13.622,"sw":0.32553125,"clr":0,"A":"left","R":[{"T":"0.62","S":2,"TS":[0,10,0,0]}]},{"x":15.375,"y":5.309,"w":92.575,"sw":0.32553125,"clr":0,"A":"left","R":[{"T":"PORTO%20ALEGRE%20-%20SARANDI","S":2,"TS":[0,10,0,0]}]},{"x":0.688,"y":5.934,"w":18.669,"sw":0.32553125,"clr":0,"A":"left","R":[{"T":"Nome","S":2,"TS":[0,10,0,0]}]},{"x":2,"y":5.934,"w":62.272,"sw":0.32553125,"clr":0,"A":"left","R":[{"T":"10089640366871","S":-1,"TS":[0,11,1,0]}]},{"x":6.688,"y":5.934,"w":45.368,"sw":0.32553125,"clr":0,"A":"left","R":[{"T":"B813674367","S":-1,"TS":[0,11,0,0]}]},{"x":10.625,"y":5.934,"w":49.021,"sw":0.32553125,"clr":0,"A":"left","R":[{"T":"Cep%20-%20Endere%C3%A7o","S":2,"TS":[0,10,0,0]}]},{"x":13.813,"y":5.934,"w":35.007,"sw":0.32553125,"clr":0,"A":"left","R":[{"T":"Nota%20Fiscal","S":2,"TS":[0,10,0,0]}]},{"x":16.5,"y":5.934,"w":26.688,"sw":0.32553125,"clr":0,"A":"left","R":[{"T":"468896","S":-1,"TS":[0,11,0,0]}]},{"x":23.063,"y":5.934,"w":62.272,"sw":0.32553125,"clr":0,"A":"left","R":[{"T":"10089640366871","S":-1,"TS":[0,11,1,0]}]},{"x":0.688,"y":6.434,"w":86.373,"sw":0.32553125,"clr":0,"A":"left","R":[{"T":"KELLY%20SOARES%20DA%20SILVA","S":2,"TS":[0,10,0,0]}]},{"x":10.875,"y":6.434,"w":154.056,"sw":0.32553125,"clr":0,"A":"left","R":[{"T":"91000001%20-%20R%20JACKSON%20DE%20FIGUEIREDO%2C1052%2C","S":2,"TS":[0,10,0,0]}]},{"x":29.313,"y":7.497,"w":85.624,"sw":0.32553125,"clr":0,"A":"left","R":[{"T":"10089640366871","S":-1,"TS":[0,15,1,0]}]},{"x":0.688,"y":8.622,"w":60.702,"sw":0.32553125,"clr":0,"A":"left","R":[{"T":"Data%3A%2018%2F09%2F2018%20Hora","S":51,"TS":[0,9,0,0]}]},{"x":4.938,"y":8.622,"w":79.362,"sw":0.32553125,"clr":0,"A":"left","R":[{"T":"Nome%20completo%20e%20Documento","S":51,"TS":[0,9,0,0]}]},{"x":10.25,"y":8.622,"w":229.776,"sw":0.32553125,"clr":0,"A":"left","R":[{"T":"Declaro%20ter%20recebido%20todas%20as%20notas%20fiscais%20constantes%20no%20conhecimento%20de%20transporte.","S":51,"TS":[0,9,0,0]}]},{"x":24.938,"y":8.622,"w":161.784,"sw":0.32553125,"clr":0,"A":"left","R":[{"T":"CT-e%2043180904884082001379570000025725611025725610","S":51,"TS":[0,9,0,0]}]},{"x":34.284,"y":8.122,"w":19.46,"sw":0.32553125,"clr":0,"A":"left","R":[{"T":"0.00","S":10,"TS":[0,14,1,0]}]},{"x":13.488,"y":2.075,"w":145.03,"sw":0.38021875,"clr":0,"A":"left","R":[{"T":"Lista%20de%20Remessas%20sem%20FRAP","S":10,"TS":[0,14,1,0]}]},{"x":1.141,"y":2.239,"w":92.568,"sw":0.40625,"clr":0,"A":"left","R":[{"T":"Ter%2C%2018%20set%202018%2012%3A13%3A16","S":-1,"TS":[0,11,0,0]}]},{"x":20.859,"y":1.404,"w":38.15,"sw":0.40625,"clr":0,"A":"left","R":[{"T":"29456","S":-1,"TS":[0,17,0,0]}]},{"x":1.141,"y":3.4800000000000004,"w":52.785,"sw":0.40625,"clr":0,"A":"left","R":[{"T":"ROTA%20HERBA","S":3,"TS":[0,12,0,0]}]},{"x":6.203,"y":3.4939999999999998,"w":217.071,"sw":0.40625,"clr":0,"A":"left","R":[{"T":"Origem%20000000378%20%20JEF%20SANTOS%20TRANSPORTES%20LTDA","S":3,"TS":[0,12,0,0]}]},{"x":7.481,"y":46.521,"w":5.724,"sw":0.38021875,"clr":0,"A":"left","R":[{"T":"1","S":9,"TS":[0,12,1,0]}]},{"x":12.79,"y":46.521,"w":5.724,"sw":0.38021875,"clr":0,"A":"left","R":[{"T":"1","S":9,"TS":[0,12,1,0]}]},{"x":17.677,"y":46.521,"w":19.98,"sw":0.38021875,"clr":0,"A":"left","R":[{"T":"0.62","S":9,"TS":[0,12,1,0]}]},{"x":23.012,"y":46.521,"w":19.98,"sw":0.38021875,"clr":0,"A":"left","R":[{"T":"0.00","S":9,"TS":[0,12,1,0]}]}],"Fields":[],"Boxsets":[]}],"Width":37.209}}